src/ECSClient.py
src/EventsClient.py
src/__init__.py
src/configManager.py
src/deployTaskDefinitions.py
src/taskDefinition.py
deploy_task_definitions-1.1.2.dist-info/METADATA
deploy_task_definitions-1.1.2.dist-info/WHEEL
deploy_task_definitions-1.1.2.dist-info/entry_points.txt
deploy_task_definitions-1.1.2.dist-info/top_level.txt
deploy_task_definitions-1.1.2.dist-info/RECORD
