Metadata-Version: 2.1
Name: deploy-task-definitions
Version: 1.1.2
Summary: Script for deploy task definitions to ECS
Home-page: https://github.com/redaptiveinc/deploy-task-definitions
Author: Mariano Gimenez
Author-email: mariano.gimenez@agileengine.com
License: unlicense
Platform: UNKNOWN
Requires-Dist: requests (==2.26.0)
Requires-Dist: python-dotenv (==0.19.1)
Requires-Dist: boto3 (==1.18.59)
Requires-Dist: botocore (==1.21.59)
